{"64":{"e":"Krabi","t":"กระบี่"},"1":{"e":"Bangkok","t":"กรุงเทพมหานคร"},"56":{"e":"Kanchanaburi","t":"กาญจนบุรี"},"34":{"e":"Kalasin","t":"กาฬสินธุ์"},"49":{"e":"Kamphaeng Phet","t":"กำแพงเพชร"},"28":{"e":"Khon Kaen","t":"ขอนแก่น"},"13":{"e":"Chanthaburi","t":"จันทบุรี"},"15":{"e":"Chachoengsao","t":"ฉะเชิงเทรา"},"11":{"e":"Chon Buri","t":"ชลบุรี"},"9":{"e":"Chai Nat","t":"ชัยนาท"},"25":{"e":"Chaiyaphum","t":"ชัยภูมิ"},"69":{"e":"Chumphon","t":"ชุมพร"},"45":{"e":"Chiang Rai","t":"เชียงราย"},"38":{"e":"Chiang Mai","t":"เชียงใหม่"},"72":{"e":"Trang","t":"ตรัง"},"14":{"e":"Trat","t":"ตราด"},"50":{"e":"Tak","t":"ตาก"},"17":{"e":"Nakhon Nayok","t":"นครนายก"},"58":{"e":"Nakhon Pathom","t":"นครปฐม"},"36":{"e":"Nakhon Phanom","t":"นครพนม"},"19":{"e":"Nakhon Ratchasima","t":"นครราชสีมา"},"63":{"e":"Nakhon Si Thammarat","t":"นครศรีธรรมราช"},"47":{"e":"Nakhon Sawan","t":"นครสวรรค์"},"3":{"e":"Nonthaburi","t":"นนทบุรี"},"76":{"e":"Narathiwat","t":"นราธิวาส"},"43":{"e":"Nan","t":"น่าน"},"77":{"e":"Bueng Kan","t":"บึงกาฬ"},"20":{"e":"Buri Ram","t":"บุรีรัมย์"},"4":{"e":"Pathum Thani","t":"ปทุมธานี"},"62":{"e":"Prachuap Khiri Khan","t":"ประจวบคีรีขันธ์"},"16":{"e":"Prachin Buri","t":"ปราจีนบุรี"},"74":{"e":"Pattani","t":"ปัตตานี"},"5":{"e":"Phra Nakhon Si Ayutthaya","t":"พระนครศรีอยุธยา"},"44":{"e":"Phayao","t":"พะเยา"},"65":{"e":"Phangnga","t":"พังงา"},"73":{"e":"Phatthalung","t":"พัทลุง"},"53":{"e":"Phichit","t":"พิจิตร"},"52":{"e":"Phitsanulok","t":"พิษณุโลก"},"61":{"e":"Phetchaburi","t":"เพชรบุรี"},"54":{"e":"Phetchabun","t":"เพชรบูรณ์"},"42":{"e":"Phrae","t":"แพร่"},"66":{"e":"Phuket","t":"ภูเก็ต"},"32":{"e":"Maha Sarakham","t":"มหาสารคาม"},"37":{"e":"Mukdahan","t":"มุกดาหาร"},"46":{"e":"Mae Hong Son","t":"แม่ฮ่องสอน"},"24":{"e":"Yasothon","t":"ยโสธร"},"75":{"e":"Yala","t":"ยะลา"},"33":{"e":"Roi Et","t":"ร้อยเอ็ด"},"68":{"e":"Ranong","t":"ระนอง"},"12":{"e":"Rayong","t":"ระยอง"},"55":{"e":"Ratchaburi","t":"ราชบุรี"},"7":{"e":"Loburi","t":"ลพบุรี"},"40":{"e":"Lampang","t":"ลำปาง"},"39":{"e":"Lamphun","t":"ลำพูน"},"30":{"e":"Loei","t":"เลย"},"22":{"e":"Si Sa Ket","t":"ศรีสะเกษ"},"35":{"e":"Sakon Nakhon","t":"สกลนคร"},"70":{"e":"Songkhla","t":"สงขลา"},"71":{"e":"Satun","t":"สตูล"},"2":{"e":"Samut Prakan","t":"สมุทรปราการ"},"60":{"e":"Samut Songkhram","t":"สมุทรสงคราม"},"59":{"e":"Samut Sakhon","t":"สมุทรสาคร"},"18":{"e":"Sa Kaeo","t":"สระแก้ว"},"10":{"e":"Saraburi","t":"สระบุรี"},"8":{"e":"Sing Buri","t":"สิงห์บุรี"},"51":{"e":"Sukhothai","t":"สุโขทัย"},"57":{"e":"Suphan Buri","t":"สุพรรณบุรี"},"67":{"e":"Surat Thani","t":"สุราษฎร์ธานี"},"21":{"e":"Surin","t":"สุรินทร์"},"31":{"e":"Nong Khai","t":"หนองคาย"},"27":{"e":"Nong Bua Lam Phu","t":"หนองบัวลำภู"},"6":{"e":"Ang Thong","t":"อ่างทอง"},"26":{"e":"Amnat Charoen","t":"อำนาจเจริญ"},"29":{"e":"Udon Thani","t":"อุดรธานี"},"41":{"e":"Uttaradit","t":"อุตรดิตถ์"},"48":{"e":"Uthai Thani","t":"อุทัยธานี"},"23":{"e":"Ubon Ratchathani","t":"อุบลราชธานี"}}